{
    "scene": {
        "name": "__tmp__playsavescene"
    },
    "gameobjects": [
        {
            "isRoot": true,
            "static": true,
            "uid": 1593266048,
            "parentUID": -1,
            "name": "Scene Root"
        },
        {
            "isRoot": false,
            "static": true,
            "uid": 714615040,
            "parentUID": 1593266048,
            "name": "runalien.fbx"
        },
        {
            "isRoot": false,
            "static": true,
            "uid": 261285008,
            "parentUID": 714615040,
            "name": "Marciano:grp_geometry"
        },
        {
            "isRoot": false,
            "static": true,
            "uid": -1411847040,
            "parentUID": 261285008,
            "name": "Marciano:geo_alien"
        },
        {
            "isRoot": false,
            "static": true,
            "uid": -2016839168,
            "parentUID": 714615040,
            "name": "Marciano:Character1_Reference"
        },
        {
            "isRoot": false,
            "static": true,
            "uid": 1830369152,
            "parentUID": -2016839168,
            "name": "Marciano:Character1_Hips"
        },
        {
            "isRoot": false,
            "static": true,
            "uid": 1875650560,
            "parentUID": 1830369152,
            "name": "Marciano:joint8"
        },
        {
            "isRoot": false,
            "static": true,
            "uid": 154507728,
            "parentUID": 1875650560,
            "name": "Marciano:joint9"
        },
        {
            "isRoot": false,
            "static": true,
            "uid": -1559008384,
            "parentUID": 1830369152,
            "name": "Marciano:joint13"
        },
        {
            "isRoot": false,
            "static": true,
            "uid": 1336526336,
            "parentUID": -1559008384,
            "name": "Marciano:joint9"
        },
        {
            "isRoot": false,
            "static": true,
            "uid": 590905472,
            "parentUID": 1830369152,
            "name": "Marciano:Character1_LeftUpLeg"
        },
        {
            "isRoot": false,
            "static": true,
            "uid": -445402624,
            "parentUID": 590905472,
            "name": "Marciano:ikHandle6"
        },
        {
            "isRoot": false,
            "static": true,
            "uid": 236067392,
            "parentUID": 590905472,
            "name": "Marciano:hlp_jt_twist_upperLeg_L"
        },
        {
            "isRoot": false,
            "static": true,
            "uid": 2010471040,
            "parentUID": 590905472,
            "name": "Marciano:Character1_LeftLeg"
        },
        {
            "isRoot": false,
            "static": true,
            "uid": 139260784,
            "parentUID": 2010471040,
            "name": "Marciano:hlp_jt_twist_lowerLeg_L"
        },
        {
            "isRoot": false,
            "static": true,
            "uid": 1492963968,
            "parentUID": 139260784,
            "name": "Marciano:joint7"
        },
        {
            "isRoot": false,
            "static": true,
            "uid": -1002876160,
            "parentUID": 2010471040,
            "name": "Marciano:Character1_LeftFoot"
        },
        {
            "isRoot": false,
            "static": true,
            "uid": -362955392,
            "parentUID": -1002876160,
            "name": "Marciano:ikHandle5"
        },
        {
            "isRoot": false,
            "static": true,
            "uid": -1741535360,
            "parentUID": -1002876160,
            "name": "Marciano:Character1_LeftToeBase"
        },
        {
            "isRoot": false,
            "static": true,
            "uid": -89387856,
            "parentUID": -1741535360,
            "name": "Marciano:Character1_LeftFootMiddle1"
        },
        {
            "isRoot": false,
            "static": true,
            "uid": -136997472,
            "parentUID": -89387856,
            "name": "Marciano:Character1_LeftFootMiddle2"
        },
        {
            "isRoot": false,
            "static": true,
            "uid": 798481152,
            "parentUID": 590905472,
            "name": "Marciano:hlp_hip_L_blendshape_forward_source"
        },
        {
            "isRoot": false,
            "static": true,
            "uid": 1571042432,
            "parentUID": 1830369152,
            "name": "Marciano:Character1_RightUpLeg"
        },
        {
            "isRoot": false,
            "static": true,
            "uid": 549696320,
            "parentUID": 1571042432,
            "name": "Marciano:hlp_jt_twist_upperLeg_R"
        },
        {
            "isRoot": false,
            "static": true,
            "uid": -1541652608,
            "parentUID": 1571042432,
            "name": "Marciano:ikHandle6"
        },
        {
            "isRoot": false,
            "static": true,
            "uid": 443678496,
            "parentUID": 1571042432,
            "name": "Marciano:Character1_RightLeg"
        },
        {
            "isRoot": false,
            "static": true,
            "uid": -172112464,
            "parentUID": 443678496,
            "name": "Marciano:hlp_jt_twist_lowerLeg_R"
        },
        {
            "isRoot": false,
            "static": true,
            "uid": -1857067392,
            "parentUID": -172112464,
            "name": "Marciano:joint7"
        },
        {
            "isRoot": false,
            "static": true,
            "uid": -1207728000,
            "parentUID": 443678496,
            "name": "Marciano:Character1_RightFoot"
        },
        {
            "isRoot": false,
            "static": true,
            "uid": -1704658560,
            "parentUID": -1207728000,
            "name": "Marciano:ikHandle7"
        },
        {
            "isRoot": false,
            "static": true,
            "uid": 971652928,
            "parentUID": -1207728000,
            "name": "Marciano:Character1_RightToeBase"
        },
        {
            "isRoot": false,
            "static": true,
            "uid": -1560375040,
            "parentUID": 971652928,
            "name": "Marciano:Character1_RightFootMiddle1"
        },
        {
            "isRoot": false,
            "static": true,
            "uid": 2103248896,
            "parentUID": -1560375040,
            "name": "Marciano:Character1_RightFootMiddle2"
        },
        {
            "isRoot": false,
            "static": true,
            "uid": -397543520,
            "parentUID": 1830369152,
            "name": "Marciano:Character1_Spine"
        },
        {
            "isRoot": false,
            "static": true,
            "uid": 1834512640,
            "parentUID": -397543520,
            "name": "Marciano:Character1_Spine1"
        },
        {
            "isRoot": false,
            "static": true,
            "uid": 603264960,
            "parentUID": 1834512640,
            "name": "Marciano:Character1_Spine2"
        },
        {
            "isRoot": false,
            "static": true,
            "uid": 1528985728,
            "parentUID": 603264960,
            "name": "Marciano:Character1_LeftShoulder"
        },
        {
            "isRoot": false,
            "static": true,
            "uid": 1232787584,
            "parentUID": 1528985728,
            "name": "Marciano:hlp_jt_twist_upperArm_L"
        },
        {
            "isRoot": false,
            "static": true,
            "uid": 1802871424,
            "parentUID": 1232787584,
            "name": "Marciano:joint4"
        },
        {
            "isRoot": false,
            "static": true,
            "uid": -1812314880,
            "parentUID": 1528985728,
            "name": "Marciano:Character1_LeftArm"
        },
        {
            "isRoot": false,
            "static": true,
            "uid": 1131657984,
            "parentUID": -1812314880,
            "name": "Marciano:ikHandle2"
        },
        {
            "isRoot": false,
            "static": true,
            "uid": 615645760,
            "parentUID": -1812314880,
            "name": "Marciano:hlp_jt_twist_upperArm_L"
        },
        {
            "isRoot": false,
            "static": true,
            "uid": 553456192,
            "parentUID": -1812314880,
            "name": "Marciano:Character1_LeftForeArm"
        },
        {
            "isRoot": false,
            "static": true,
            "uid": -1644470272,
            "parentUID": 553456192,
            "name": "Marciano:hlp_jt_twist_lowerArm_L"
        },
        {
            "isRoot": false,
            "static": true,
            "uid": -357999936,
            "parentUID": -1644470272,
            "name": "Marciano:joint2"
        },
        {
            "isRoot": false,
            "static": true,
            "uid": 1882881664,
            "parentUID": 553456192,
            "name": "Marciano:Character1_LeftHand"
        },
        {
            "isRoot": false,
            "static": true,
            "uid": 1269820288,
            "parentUID": 1882881664,
            "name": "Marciano:ikHandle1"
        },
        {
            "isRoot": false,
            "static": true,
            "uid": 1340903680,
            "parentUID": 1882881664,
            "name": "Marciano:Character1_LeftHandThumb1"
        },
        {
            "isRoot": false,
            "static": true,
            "uid": 14120446,
            "parentUID": 1340903680,
            "name": "Marciano:Character1_LeftHandThumb2"
        },
        {
            "isRoot": false,
            "static": true,
            "uid": 1868935936,
            "parentUID": 14120446,
            "name": "Marciano:Character1_LeftHandThumb3"
        },
        {
            "isRoot": false,
            "static": true,
            "uid": -473400736,
            "parentUID": 1868935936,
            "name": "Marciano:Character1_LeftHandThumb4"
        },
        {
            "isRoot": false,
            "static": true,
            "uid": 784219264,
            "parentUID": 1882881664,
            "name": "Marciano:Character1_LeftHandIndex1"
        },
        {
            "isRoot": false,
            "static": true,
            "uid": 1408970368,
            "parentUID": 784219264,
            "name": "Marciano:Character1_LeftHandIndex2"
        },
        {
            "isRoot": false,
            "static": true,
            "uid": 1347059840,
            "parentUID": 1408970368,
            "name": "Marciano:Character1_LeftHandIndex3"
        },
        {
            "isRoot": false,
            "static": true,
            "uid": 1563565696,
            "parentUID": 1347059840,
            "name": "Marciano:Character1_LeftHandIndex4"
        },
        {
            "isRoot": false,
            "static": true,
            "uid": 1121575296,
            "parentUID": 1882881664,
            "name": "Marciano:Character1_LeftHandMiddle1"
        },
        {
            "isRoot": false,
            "static": true,
            "uid": 1630348928,
            "parentUID": 1121575296,
            "name": "Marciano:Character1_LeftHandMiddle2"
        },
        {
            "isRoot": false,
            "static": true,
            "uid": 663789056,
            "parentUID": 1630348928,
            "name": "Marciano:Character1_LeftHandMiddle3"
        },
        {
            "isRoot": false,
            "static": true,
            "uid": -1484469504,
            "parentUID": 663789056,
            "name": "Marciano:Character1_LeftHandMiddle4"
        },
        {
            "isRoot": false,
            "static": true,
            "uid": -1467325184,
            "parentUID": 603264960,
            "name": "Marciano:Character1_RightShoulder"
        },
        {
            "isRoot": false,
            "static": true,
            "uid": 1192489856,
            "parentUID": -1467325184,
            "name": "Marciano:hlp_jt_twist_upperArm_R"
        },
        {
            "isRoot": false,
            "static": true,
            "uid": 425161088,
            "parentUID": 1192489856,
            "name": "Marciano:joint4"
        },
        {
            "isRoot": false,
            "static": true,
            "uid": 1550706304,
            "parentUID": -1467325184,
            "name": "Marciano:Character1_RightArm"
        },
        {
            "isRoot": false,
            "static": true,
            "uid": -967872192,
            "parentUID": 1550706304,
            "name": "Marciano:hlp_jt_twist_upperArm_R"
        },
        {
            "isRoot": false,
            "static": true,
            "uid": -698441728,
            "parentUID": 1550706304,
            "name": "Marciano:ikHandle3"
        },
        {
            "isRoot": false,
            "static": true,
            "uid": -388379776,
            "parentUID": 1550706304,
            "name": "Marciano:Character1_RightForeArm"
        },
        {
            "isRoot": false,
            "static": true,
            "uid": 2118833664,
            "parentUID": -388379776,
            "name": "Marciano:hlp_jt_twist_lowerArm_R"
        },
        {
            "isRoot": false,
            "static": true,
            "uid": 425852832,
            "parentUID": 2118833664,
            "name": "Marciano:joint2"
        },
        {
            "isRoot": false,
            "static": true,
            "uid": 417723200,
            "parentUID": -388379776,
            "name": "Marciano:Character1_RightHand"
        },
        {
            "isRoot": false,
            "static": true,
            "uid": -256659200,
            "parentUID": 417723200,
            "name": "Marciano:ikHandle4"
        },
        {
            "isRoot": false,
            "static": true,
            "uid": -702691008,
            "parentUID": 417723200,
            "name": "Marciano:Character1_RightHandThumb1"
        },
        {
            "isRoot": false,
            "static": true,
            "uid": -805299200,
            "parentUID": -702691008,
            "name": "Marciano:Character1_RightHandThumb2"
        },
        {
            "isRoot": false,
            "static": true,
            "uid": 1012490048,
            "parentUID": -805299200,
            "name": "Marciano:Character1_RightHandThumb3"
        },
        {
            "isRoot": false,
            "static": true,
            "uid": -1520976896,
            "parentUID": 1012490048,
            "name": "Marciano:Character1_RightHandThumb4"
        },
        {
            "isRoot": false,
            "static": true,
            "uid": -211123744,
            "parentUID": 417723200,
            "name": "Marciano:Character1_RightHandIndex1"
        },
        {
            "isRoot": false,
            "static": true,
            "uid": -1775365632,
            "parentUID": -211123744,
            "name": "Marciano:Character1_RightHandIndex2"
        },
        {
            "isRoot": false,
            "static": true,
            "uid": 250299104,
            "parentUID": -1775365632,
            "name": "Marciano:Character1_RightHandIndex3"
        },
        {
            "isRoot": false,
            "static": true,
            "uid": 693538944,
            "parentUID": 250299104,
            "name": "Marciano:Character1_RightHandIndex4"
        },
        {
            "isRoot": false,
            "static": true,
            "uid": -1711461376,
            "parentUID": 417723200,
            "name": "Marciano:Character1_RightHandMiddle1"
        },
        {
            "isRoot": false,
            "static": true,
            "uid": 968746688,
            "parentUID": -1711461376,
            "name": "Marciano:Character1_RightHandMiddle2"
        },
        {
            "isRoot": false,
            "static": true,
            "uid": -2058729216,
            "parentUID": 968746688,
            "name": "Marciano:Character1_RightHandMiddle3"
        },
        {
            "isRoot": false,
            "static": true,
            "uid": -584565952,
            "parentUID": -2058729216,
            "name": "Marciano:Character1_RightHandMiddle4"
        },
        {
            "isRoot": false,
            "static": true,
            "uid": 1639236352,
            "parentUID": 603264960,
            "name": "Marciano:Character1_Neck"
        },
        {
            "isRoot": false,
            "static": true,
            "uid": -591561792,
            "parentUID": 1639236352,
            "name": "Marciano:Character1_Head"
        },
        {
            "isRoot": false,
            "static": true,
            "uid": 1633352576,
            "parentUID": 1830369152,
            "name": "Marciano:hlp_hip_L_blendshape_sideways_target"
        },
        {
            "isRoot": false,
            "static": true,
            "uid": -768364992,
            "parentUID": 1830369152,
            "name": "Marciano:hlp_hip_L_blendshape_forward_target"
        },
        {
            "isRoot": false,
            "static": true,
            "uid": 816238528,
            "parentUID": 714615040,
            "name": "Marciano:distance_dimensions"
        },
        {
            "isRoot": false,
            "static": true,
            "uid": 408108192,
            "parentUID": 816238528,
            "name": "Marciano:distanceDimension1"
        },
        {
            "isRoot": false,
            "static": true,
            "uid": -1438609280,
            "parentUID": 816238528,
            "name": "Marciano:distanceDimension2"
        },
        {
            "isRoot": false,
            "static": true,
            "uid": 243113328,
            "parentUID": 714615040,
            "name": "Marciano:Character1_Ctrl_Reference"
        }
    ],
    "components": [
        {
            "type": 2,
            "parentUID": 1593266048,
            "position": {
                "x": 0,
                "y": 0,
                "z": 0
            },
            "rotation": {
                "x": 0,
                "y": 0,
                "z": 0,
                "w": 1
            },
            "scale": {
                "x": 0,
                "y": 0,
                "z": 0
            }
        },
        {
            "type": 2,
            "parentUID": 714615040,
            "position": {
                "x": 0,
                "y": 0,
                "z": 0
            },
            "rotation": {
                "x": 0,
                "y": 0,
                "z": 0,
                "w": 1
            },
            "scale": {
                "x": 1,
                "y": 1,
                "z": 1
            }
        },
        {},
        {
            "type": 2,
            "parentUID": 261285008,
            "position": {
                "x": 0,
                "y": 0,
                "z": 0
            },
            "rotation": {
                "x": 0,
                "y": 0,
                "z": 0,
                "w": 1
            },
            "scale": {
                "x": 1,
                "y": 1,
                "z": 1
            }
        },
        {
            "type": 2,
            "parentUID": -1411847040,
            "position": {
                "x": 0,
                "y": 0,
                "z": 0
            },
            "rotation": {
                "x": 0,
                "y": 0,
                "z": 0,
                "w": 1
            },
            "scale": {
                "x": 1,
                "y": 1,
                "z": 1
            }
        },
        {
            "type": 0,
            "parentUID": -1411847040,
            "path": "Library\/Meshes\/_88.mymesh",
            "rawpath": "C:\\Users\\Usuario\\Documents\\GitHub\\3dEngine\\Game\\Assets\\runalien.fbx",
            "meshdoc": "84688500fab5a9248517554983c1238b"
        },
        {},
        {
            "type": 2,
            "parentUID": -2016839168,
            "position": {
                "x": 0,
                "y": 0,
                "z": 0
            },
            "rotation": {
                "x": 0,
                "y": 0,
                "z": 0,
                "w": 1
            },
            "scale": {
                "x": 1,
                "y": 1,
                "z": 1
            }
        },
        {
            "type": 2,
            "parentUID": 1830369152,
            "position": {
                "x": 1.5228491747620865e-06,
                "y": 4.449462890625,
                "z": -9.9272416264284402e-05
            },
            "rotation": {
                "x": 0.2565123438835144,
                "y": -0.14279095828533173,
                "z": -0.039458531886339188,
                "w": 0.95512056350708008
            },
            "scale": {
                "x": 0.99999994039535522,
                "y": 0.99999994039535522,
                "z": 1
            }
        },
        {
            "type": 2,
            "parentUID": 1875650560,
            "position": {
                "x": 1.3073379993438721,
                "y": 0.74527794122695923,
                "z": -0.14803381264209747
            },
            "rotation": {
                "x": 0.41052019596099854,
                "y": -0.51484555006027222,
                "z": -0.48469996452331543,
                "w": 0.57573705911636353
            },
            "scale": {
                "x": 0.99999994039535522,
                "y": 0.99999994039535522,
                "z": 1
            }
        },
        {
            "type": 2,
            "parentUID": 154507728,
            "position": {
                "x": 0.75964254140853882,
                "y": -8.3266726846886741e-17,
                "z": 2.0857086434416392e-19
            },
            "rotation": {
                "x": -0.44864434003829956,
                "y": 0.54655122756958008,
                "z": 0.44864436984062195,
                "w": 0.54655122756958008
            },
            "scale": {
                "x": 1,
                "y": 0.99999994039535522,
                "z": 0.99999994039535522
            }
        },
        {
            "type": 2,
            "parentUID": -1559008384,
            "position": {
                "x": -1.3073400259017944,
                "y": 0.74527835845947266,
                "z": -0.14803400635719299
            },
            "rotation": {
                "x": -0.48419544100761414,
                "y": -0.37449079751968384,
                "z": 0.59979718923568726,
                "w": 0.51532000303268433
            },
            "scale": {
                "x": 0.99999994039535522,
                "y": 0.99999994039535522,
                "z": 1
            }
        },
        {
            "type": 2,
            "parentUID": 1336526336,
            "position": {
                "x": -0.75964349508285522,
                "y": -5.2343538392563005e-09,
                "z": -4.4408920985006262e-16
            },
            "rotation": {
                "x": -0.44864434003829956,
                "y": 0.54655122756958008,
                "z": 0.44864436984062195,
                "w": 0.54655122756958008
            },
            "scale": {
                "x": 1,
                "y": 0.99999994039535522,
                "z": 0.99999994039535522
            }
        },
        {
            "type": 2,
            "parentUID": 590905472,
            "position": {
                "x": 1.3073388338088989,
                "y": 0.00019898283062502742,
                "z": 9.6963404416783305e-08
            },
            "rotation": {
                "x": -0.52282208204269409,
                "y": 0.06675836443901062,
                "z": 0.1741088479757309,
                "w": 0.83179712295532227
            },
            "scale": {
                "x": 1,
                "y": 1,
                "z": 0.99999994039535522
            }
        },
        {
            "type": 2,
            "parentUID": -445402624,
            "position": {
                "x": 0,
                "y": 0,
                "z": 0
            },
            "rotation": {
                "x": 0.44864434003829956,
                "y": -0.54655122756958008,
                "z": -0.44864434003829956,
                "w": 0.54655122756958008
            },
            "scale": {
                "x": 0.99999994039535522,
                "y": 0.99999994039535522,
                "z": 1
            }
        },
        {
            "type": 2,
            "parentUID": 236067392,
            "position": {
                "x": 3.5790375108035732e-08,
                "y": -0.86840981245040894,
                "z": 0.17253744602203369
            },
            "rotation": {
                "x": 0.48470008373260498,
                "y": -0.57573717832565308,
                "z": -0.41052007675170898,
                "w": 0.51484543085098267
            },
            "scale": {
                "x": 0.99999994039535522,
                "y": 0.99999994039535522,
                "z": 1
            }
        },
        {
            "type": 2,
            "parentUID": 2010471040,
            "position": {
                "x": -7.3800370046228636e-06,
                "y": -1.7998754978179932,
                "z": 0.37469121813774109
            },
            "rotation": {
                "x": 0.28072410821914673,
                "y": 0.0076202661730349064,
                "z": 0.0044741635210812092,
                "w": 0.9597477912902832
            },
            "scale": {
                "x": 1,
                "y": 1,
                "z": 1
            }
        },
        {
            "type": 2,
            "parentUID": 139260784,
            "position": {
                "x": 3.5790371555322054e-08,
                "y": -0.81359738111495972,
                "z": -0.21915002167224884
            },
            "rotation": {
                "x": -0.44230231642723083,
                "y": 0.5688508152961731,
                "z": -0.42001041769981384,
                "w": 0.55169612169265747
            },
            "scale": {
                "x": 0.99999994039535522,
                "y": 0.99999994039535522,
                "z": 1
            }
        },
        {
            "type": 2,
            "parentUID": 1492963968,
            "position": {
                "x": 0.99262142181396484,
                "y": -1.6653345369377348e-16,
                "z": -1.1020311572340234e-16
            },
            "rotation": {
                "x": 0.4312417209148407,
                "y": -0.56038433313369751,
                "z": 0.43124175071716309,
                "w": 0.56038427352905273
            },
            "scale": {
                "x": 1,
                "y": 1,
                "z": 1
            }
        },
        {
            "type": 2,
            "parentUID": -1002876160,
            "position": {
                "x": -1.8379995481154765e-07,
                "y": -1.773110032081604,
                "z": -0.47338306903839111
            },
            "rotation": {
                "x": 0.00019940252241212875,
                "y": 0.042946718633174896,
                "z": -0.13018862903118134,
                "w": 0.9905586838722229
            },
            "scale": {
                "x": 0.99999994039535522,
                "y": 0.99999994039535522,
                "z": 1
            }
        },
        {
            "type": 2,
            "parentUID": -362955392,
            "position": {
                "x": 0,
                "y": 0,
                "z": 0
            },
            "rotation": {
                "x": -0.43124169111251831,
                "y": 0.56038433313369751,
                "z": -0.43124169111251831,
                "w": 0.56038433313369751
            },
            "scale": {
                "x": 0.99999994039535522,
                "y": 0.99999994039535522,
                "z": 1
            }
        },
        {
            "type": 2,
            "parentUID": -1741535360,
            "position": {
                "x": 9.6925487014232203e-07,
                "y": -1.0948116779327393,
                "z": 2.0311951637268066
            },
            "rotation": {
                "x": -0.20646937191486359,
                "y": 0,
                "z": 0,
                "w": 0.97845315933227539
            },
            "scale": {
                "x": 1,
                "y": 1,
                "z": 1
            }
        },
        {
            "type": 2,
            "parentUID": -89387856,
            "position": {
                "x": 0.00067148415837436914,
                "y": -5.5659103992411474e-09,
                "z": 3.2069092270603505e-08
            },
            "rotation": {
                "x": 0,
                "y": 0,
                "z": 0,
                "w": 1
            },
            "scale": {
                "x": 1,
                "y": 1,
                "z": 1
            }
        },
        {
            "type": 2,
            "parentUID": -136997472,
            "position": {
                "x": -5.6588461916362576e-08,
                "y": 1.7062498613995558e-07,
                "z": 1.2044209241867065
            },
            "rotation": {
                "x": 0,
                "y": 0,
                "z": 0,
                "w": 1
            },
            "scale": {
                "x": 1,
                "y": 1,
                "z": 1
            }
        },
        {
            "type": 2,
            "parentUID": 798481152,
            "position": {
                "x": 3.5790371555322054e-08,
                "y": -1.7998734712600708,
                "z": 0.38774123787879944
            },
            "rotation": {
                "x": 0,
                "y": 0,
                "z": 0,
                "w": 1
            },
            "scale": {
                "x": 1,
                "y": 1,
                "z": 1
            }
        },
        {
            "type": 2,
            "parentUID": 1571042432,
            "position": {
                "x": -1.3073393106460571,
                "y": 0.00019922433421015739,
                "z": -4.2148820966758649e-07
            },
            "rotation": {
                "x": -0.089551337063312531,
                "y": 0.068512238562107086,
                "z": -0.20301727950572968,
                "w": 0.97266161441802979
            },
            "scale": {
                "x": 0.99999994039535522,
                "y": 0.99999994039535522,
                "z": 0.99999994039535522
            }
        },
        {
            "type": 2,
            "parentUID": 549696320,
            "position": {
                "x": -2.0364464035083074e-06,
                "y": -0.86841040849685669,
                "z": 0.17253699898719788
            },
            "rotation": {
                "x": -0.5997968316078186,
                "y": -0.51531964540481567,
                "z": 0.48419588804244995,
                "w": 0.37449127435684204
            },
            "scale": {
                "x": 0.99999994039535522,
                "y": 0.99999988079071045,
                "z": 0.99999994039535522
            }
        },
        {
            "type": 2,
            "parentUID": -1541652608,
            "position": {
                "x": 0,
                "y": 0,
                "z": 0
            },
            "rotation": {
                "x": -0.54655122756958008,
                "y": -0.44864439964294434,
                "z": 0.54655122756958008,
                "w": 0.44864434003829956
            },
            "scale": {
                "x": 0.99999994039535522,
                "y": 0.99999994039535522,
                "z": 1
            }
        },
        {
            "type": 2,
            "parentUID": 443678496,
            "position": {
                "x": 4.9375012167729437e-07,
                "y": -1.7998749017715454,
                "z": 0.37469980120658875
            },
            "rotation": {
                "x": 0.57058113813400269,
                "y": 0.082101136445999146,
                "z": 0.098124608397483826,
                "w": 0.81121397018432617
            },
            "scale": {
                "x": 1,
                "y": 0.99999994039535522,
                "z": 1
            }
        },
        {
            "type": 2,
            "parentUID": -172112464,
            "position": {
                "x": -2.0364464035083074e-06,
                "y": -0.81359702348709106,
                "z": -0.21914997696876526
            },
            "rotation": {
                "x": 0.59574401378631592,
                "y": 0.47831428050994873,
                "z": 0.52078354358673096,
                "w": 0.38090544939041138
            },
            "scale": {
                "x": 0.99999994039535522,
                "y": 0.99999994039535522,
                "z": 1
            }
        },
        {
            "type": 2,
            "parentUID": -1857067392,
            "position": {
                "x": -0.99261957406997681,
                "y": -5.7010015552805271e-07,
                "z": 4.4408920985006262e-16
            },
            "rotation": {
                "x": 0.4312417209148407,
                "y": -0.56038433313369751,
                "z": 0.43124175071716309,
                "w": 0.56038427352905273
            },
            "scale": {
                "x": 1,
                "y": 1,
                "z": 1
            }
        },
        {
            "type": 2,
            "parentUID": -1207728000,
            "position": {
                "x": 1.9959924202339607e-07,
                "y": -1.7731094360351563,
                "z": -0.47338363528251648
            },
            "rotation": {
                "x": 0.28008052706718445,
                "y": 0.096376150846481323,
                "z": -0.046135939657688141,
                "w": 0.95401155948638916
            },
            "scale": {
                "x": 1,
                "y": 1,
                "z": 1
            }
        },
        {
            "type": 2,
            "parentUID": -1704658560,
            "position": {
                "x": 0,
                "y": 0,
                "z": 0
            },
            "rotation": {
                "x": 0.56038433313369751,
                "y": 0.43124175071716309,
                "z": 0.56038433313369751,
                "w": 0.43124169111251831
            },
            "scale": {
                "x": 0.99999994039535522,
                "y": 0.99999994039535522,
                "z": 1
            }
        },
        {
            "type": 2,
            "parentUID": 971652928,
            "position": {
                "x": -6.0809418300777907e-07,
                "y": -1.0948114395141602,
                "z": 2.0311923027038574
            },
            "rotation": {
                "x": -0.0069511644542217255,
                "y": 0,
                "z": 0,
                "w": 0.99997591972351074
            },
            "scale": {
                "x": 1,
                "y": 1,
                "z": 1
            }
        },
        {
            "type": 2,
            "parentUID": -1560375040,
            "position": {
                "x": -0.00067150592803955078,
                "y": -1.3401562171111436e-07,
                "z": -1.8800545831254567e-07
            },
            "rotation": {
                "x": 0,
                "y": 0,
                "z": 0,
                "w": 1
            },
            "scale": {
                "x": 1,
                "y": 1,
                "z": 1
            }
        },
        {
            "type": 2,
            "parentUID": 2103248896,
            "position": {
                "x": 1.785551717148337e-06,
                "y": 9.7988461789100256e-08,
                "z": 1.204420804977417
            },
            "rotation": {
                "x": 0,
                "y": 0,
                "z": 0,
                "w": 1
            },
            "scale": {
                "x": 1,
                "y": 1,
                "z": 1
            }
        },
        {
            "type": 2,
            "parentUID": -397543520,
            "position": {
                "x": -3.5715206081476936e-07,
                "y": 1.1881914138793945,
                "z": 6.866250146231323e-08
            },
            "rotation": {
                "x": 0.026986515149474144,
                "y": 0,
                "z": 0,
                "w": 0.99963587522506714
            },
            "scale": {
                "x": 1,
                "y": 1,
                "z": 1
            }
        },
        {
            "type": 2,
            "parentUID": 1834512640,
            "position": {
                "x": 4.2049956050504989e-07,
                "y": 1.572748064994812,
                "z": 4.069576675647113e-07
            },
            "rotation": {
                "x": 0.053953129798173904,
                "y": 0,
                "z": 0,
                "w": 0.99854356050491333
            },
            "scale": {
                "x": 1,
                "y": 1,
                "z": 1
            }
        },
        {
            "type": 2,
            "parentUID": 603264960,
            "position": {
                "x": 3.1852655979491828e-07,
                "y": 1.5727483034133911,
                "z": -1.40927014058434e-07
            },
            "rotation": {
                "x": 0.053953230381011963,
                "y": 0,
                "z": 0,
                "w": 0.99854356050491333
            },
            "scale": {
                "x": 1,
                "y": 0.99999994039535522,
                "z": 0.99999994039535522
            }
        },
        {
            "type": 2,
            "parentUID": 1528985728,
            "position": {
                "x": 0.20696912705898285,
                "y": 1.4808237552642822,
                "z": 5.9503388882831132e-08
            },
            "rotation": {
                "x": 0,
                "y": 0,
                "z": 0,
                "w": 1
            },
            "scale": {
                "x": 1,
                "y": 1,
                "z": 1
            }
        },
        {
            "type": 2,
            "parentUID": 1232787584,
            "position": {
                "x": 0.16009247303009033,
                "y": 0.30079108476638794,
                "z": -0.070138059556484222
            },
            "rotation": {
                "x": -0.2893105149269104,
                "y": 0.16553759574890137,
                "z": -0.41940984129905701,
                "w": 0.84438860416412354
            },
            "scale": {
                "x": 1,
                "y": 1,
                "z": 0.99999994039535522
            }
        },
        {
            "type": 2,
            "parentUID": 1802871424,
            "position": {
                "x": 0.72214668989181519,
                "y": -1.2490009027033011e-16,
                "z": -1.0140951414130626e-17
            },
            "rotation": {
                "x": 0.013970835134387016,
                "y": -0.027705084532499313,
                "z": 0.45004415512084961,
                "w": 0.89246708154678345
            },
            "scale": {
                "x": 0.99999994039535522,
                "y": 1,
                "z": 0.99999994039535522
            }
        },
        {
            "type": 2,
            "parentUID": -1812314880,
            "position": {
                "x": 0.58860361576080322,
                "y": -0.27986824512481689,
                "z": -0.096768252551555634
            },
            "rotation": {
                "x": 0.1426549106836319,
                "y": 0.44403097033500671,
                "z": 0.15253052115440369,
                "w": 0.87133252620697021
            },
            "scale": {
                "x": 1,
                "y": 1,
                "z": 0.99999994039535522
            }
        },
        {
            "type": 2,
            "parentUID": 1131657984,
            "position": {
                "x": 0,
                "y": 0,
                "z": 0
            },
            "rotation": {
                "x": -0.013970833271741867,
                "y": 0.027705082669854164,
                "z": -0.45004415512084961,
                "w": 0.89246708154678345
            },
            "scale": {
                "x": 1,
                "y": 1,
                "z": 0.99999994039535522
            }
        },
        {
            "type": 2,
            "parentUID": 615645760,
            "position": {
                "x": 0.87653625011444092,
                "y": -1.1967500448226929,
                "z": -0.047005206346511841
            },
            "rotation": {
                "x": 0.26273727416992188,
                "y": -0.11284340173006058,
                "z": -0.43654745817184448,
                "w": 0.8530309796333313
            },
            "scale": {
                "x": 1,
                "y": 1,
                "z": 0.99999994039535522
            }
        },
        {
            "type": 2,
            "parentUID": 553456192,
            "position": {
                "x": 1.7332342863082886,
                "y": -2.3499383926391602,
                "z": -0.086765997111797333
            },
            "rotation": {
                "x": 0.0032125215511769056,
                "y": -0.69209706783294678,
                "z": -0.0036754829343408346,
                "w": 0.72178804874420166
            },
            "scale": {
                "x": 1,
                "y": 1,
                "z": 1
            }
        },
        {
            "type": 2,
            "parentUID": -1644470272,
            "position": {
                "x": 0.85344600677490234,
                "y": -1.1749505996704102,
                "z": 0.32607850432395935
            },
            "rotation": {
                "x": -0.34646588563919067,
                "y": 0.057928387075662613,
                "z": -0.45169901847839355,
                "w": 0.82010585069656372
            },
            "scale": {
                "x": 1,
                "y": 0.99999994039535522,
                "z": 1
            }
        },
        {
            "type": 2,
            "parentUID": -357999936,
            "position": {
                "x": 1.4348434209823608,
                "y": 1.457167719820518e-16,
                "z": -1.1623850340527505e-16
            },
            "rotation": {
                "x": -0.076842643320560455,
                "y": 0.15983131527900696,
                "z": 0.42642933130264282,
                "w": 0.88696515560150146
            },
            "scale": {
                "x": 0.99999994039535522,
                "y": 1,
                "z": 1
            }
        },
        {
            "type": 2,
            "parentUID": 1882881664,
            "position": {
                "x": 1.693151593208313,
                "y": -2.2955904006958008,
                "z": 0.63886606693267822
            },
            "rotation": {
                "x": -0.26528626680374146,
                "y": 0.36007148027420044,
                "z": -0.10091756284236908,
                "w": 0.88869988918304443
            },
            "scale": {
                "x": 1,
                "y": 1,
                "z": 1
            }
        },
        {
            "type": 2,
            "parentUID": 1269820288,
            "position": {
                "x": 0,
                "y": 0,
                "z": 0
            },
            "rotation": {
                "x": 0.076842673122882843,
                "y": -0.15983131527900696,
                "z": -0.42642930150032043,
                "w": 0.88696515560150146
            },
            "scale": {
                "x": 1,
                "y": 0.99999994039535522,
                "z": 1
            }
        },
        {
            "type": 2,
            "parentUID": 1340903680,
            "position": {
                "x": -0.041702974587678909,
                "y": -0.41237744688987732,
                "z": 0.45352235436439514
            },
            "rotation": {
                "x": 0,
                "y": 0,
                "z": 0,
                "w": 1
            },
            "scale": {
                "x": 1,
                "y": 1,
                "z": 1
            }
        },
        {
            "type": 2,
            "parentUID": 14120446,
            "position": {
                "x": -0.20675946772098541,
                "y": -0.28766068816184998,
                "z": 0.29150739312171936
            },
            "rotation": {
                "x": 0,
                "y": 0,
                "z": 0,
                "w": 1
            },
            "scale": {
                "x": 1,
                "y": 1,
                "z": 1
            }
        },
        {
            "type": 2,
            "parentUID": 1868935936,
            "position": {
                "x": -0.12375091016292572,
                "y": -0.30169901251792908,
                "z": 0.17823685705661774
            },
            "rotation": {
                "x": 0,
                "y": 0,
                "z": 0,
                "w": 1
            },
            "scale": {
                "x": 1,
                "y": 1,
                "z": 1
            }
        },
        {
            "type": 2,
            "parentUID": -473400736,
            "position": {
                "x": -0.15082064270973206,
                "y": -0.39155426621437073,
                "z": 0.10519587248563766
            },
            "rotation": {
                "x": 0,
                "y": 0,
                "z": 0,
                "w": 1
            },
            "scale": {
                "x": 1,
                "y": 1,
                "z": 1
            }
        },
        {
            "type": 2,
            "parentUID": 784219264,
            "position": {
                "x": 0.35671466588973999,
                "y": -1.2270691394805908,
                "z": 0.4871179461479187
            },
            "rotation": {
                "x": 0,
                "y": 0,
                "z": 0,
                "w": 1
            },
            "scale": {
                "x": 1,
                "y": 1,
                "z": 1
            }
        },
        {
            "type": 2,
            "parentUID": 1408970368,
            "position": {
                "x": -0.059539850801229477,
                "y": -0.4933905303478241,
                "z": 0.014719286002218723
            },
            "rotation": {
                "x": 0,
                "y": 0,
                "z": 0,
                "w": 1
            },
            "scale": {
                "x": 1,
                "y": 1,
                "z": 1
            }
        },
        {
            "type": 2,
            "parentUID": 1347059840,
            "position": {
                "x": -0.16221217811107635,
                "y": -0.39550879597663879,
                "z": -0.031543530523777008
            },
            "rotation": {
                "x": 0,
                "y": 0,
                "z": 0,
                "w": 1
            },
            "scale": {
                "x": 1,
                "y": 1,
                "z": 1
            }
        },
        {
            "type": 2,
            "parentUID": 1563565696,
            "position": {
                "x": -0.2174537181854248,
                "y": -0.3343372642993927,
                "z": -0.029786240309476852
            },
            "rotation": {
                "x": 0,
                "y": 0,
                "z": 0,
                "w": 1
            },
            "scale": {
                "x": 1,
                "y": 1,
                "z": 1
            }
        },
        {
            "type": 2,
            "parentUID": 1121575296,
            "position": {
                "x": 0.30260899662971497,
                "y": -1.2290676832199097,
                "z": -0.25764575600624084
            },
            "rotation": {
                "x": 0,
                "y": 0,
                "z": 0,
                "w": 1
            },
            "scale": {
                "x": 1,
                "y": 1,
                "z": 1
            }
        },
        {
            "type": 2,
            "parentUID": 1630348928,
            "position": {
                "x": -0.084515511989593506,
                "y": -0.52465677261352539,
                "z": 0.028078258037567139
            },
            "rotation": {
                "x": 0,
                "y": 0,
                "z": 0,
                "w": 1
            },
            "scale": {
                "x": 1,
                "y": 1,
                "z": 1
            }
        },
        {
            "type": 2,
            "parentUID": 663789056,
            "position": {
                "x": -0.15169574320316315,
                "y": -0.29501622915267944,
                "z": 0.040000922977924347
            },
            "rotation": {
                "x": 0,
                "y": 0,
                "z": 0,
                "w": 1
            },
            "scale": {
                "x": 1,
                "y": 1,
                "z": 1
            }
        },
        {
            "type": 2,
            "parentUID": -1484469504,
            "position": {
                "x": -0.18491268157958984,
                "y": -0.29434129595756531,
                "z": 0.070213459432125092
            },
            "rotation": {
                "x": 0,
                "y": 0,
                "z": 0,
                "w": 1
            },
            "scale": {
                "x": 1,
                "y": 1,
                "z": 1
            }
        },
        {
            "type": 2,
            "parentUID": -1467325184,
            "position": {
                "x": -0.20696856081485748,
                "y": 1.4808238744735718,
                "z": -1.0018700180580709e-07
            },
            "rotation": {
                "x": 0,
                "y": 0,
                "z": 0,
                "w": 1
            },
            "scale": {
                "x": 1,
                "y": 1,
                "z": 1
            }
        },
        {
            "type": 2,
            "parentUID": 1192489856,
            "position": {
                "x": -0.16009223461151123,
                "y": 0.30082783102989197,
                "z": -0.070138096809387207
            },
            "rotation": {
                "x": 0.86610442399978638,
                "y": 0.43207064270973206,
                "z": 0.1289345920085907,
                "w": 0.2157638818025589
            },
            "scale": {
                "x": 1,
                "y": 1,
                "z": 0.99999988079071045
            }
        },
        {
            "type": 2,
            "parentUID": 425161088,
            "position": {
                "x": -0.72218018770217896,
                "y": 2.3875922124716453e-05,
                "z": -7.6841814689032617e-08
            },
            "rotation": {
                "x": 0.013970835134387016,
                "y": -0.027705084532499313,
                "z": 0.45004415512084961,
                "w": 0.89246708154678345
            },
            "scale": {
                "x": 0.99999994039535522,
                "y": 1,
                "z": 0.99999994039535522
            }
        },
        {
            "type": 2,
            "parentUID": 1550706304,
            "position": {
                "x": -0.58860373497009277,
                "y": -0.27986779808998108,
                "z": -0.09676872193813324
            },
            "rotation": {
                "x": -0.40012013912200928,
                "y": 0.095864966511726379,
                "z": -0.2384473979473114,
                "w": 0.87969130277633667
            },
            "scale": {
                "x": 0.99999994039535522,
                "y": 0.99999994039535522,
                "z": 1
            }
        },
        {
            "type": 2,
            "parentUID": -967872192,
            "position": {
                "x": -0.87653744220733643,
                "y": -1.1967542171478271,
                "z": -0.047005511820316315
            },
            "rotation": {
                "x": 0.87243402004241943,
                "y": 0.44462192058563232,
                "z": -0.074957720935344696,
                "w": -0.18855132162570953
            },
            "scale": {
                "x": 1,
                "y": 1,
                "z": 0.99999988079071045
            }
        },
        {
            "type": 2,
            "parentUID": -698441728,
            "position": {
                "x": 0,
                "y": 0,
                "z": 0
            },
            "rotation": {
                "x": 0.89246708154678345,
                "y": 0.45004415512084961,
                "z": 0.027705106884241104,
                "w": 0.013970873318612576
            },
            "scale": {
                "x": 1,
                "y": 1,
                "z": 0.99999988079071045
            }
        },
        {
            "type": 2,
            "parentUID": -388379776,
            "position": {
                "x": -1.7332369089126587,
                "y": -2.3499352931976318,
                "z": -0.086764968931674957
            },
            "rotation": {
                "x": -0.26899534463882446,
                "y": 0.59560829401016235,
                "z": -0.15813450515270233,
                "w": 0.74019312858581543
            },
            "scale": {
                "x": 0.99999994039535522,
                "y": 1,
                "z": 1
            }
        },
        {
            "type": 2,
            "parentUID": 2118833664,
            "position": {
                "x": -0.85344409942626953,
                "y": -1.17494797706604,
                "z": 0.32607820630073547
            },
            "rotation": {
                "x": 0.83768999576568604,
                "y": 0.45417654514312744,
                "z": 0.033336199820041656,
                "w": 0.30147618055343628
            },
            "scale": {
                "x": 1,
                "y": 0.99999994039535522,
                "z": 1
            }
        },
        {
            "type": 2,
            "parentUID": 425852832,
            "position": {
                "x": -1.4348458051681519,
                "y": -4.3563450162764639e-06,
                "z": 1.638685944271856e-06
            },
            "rotation": {
                "x": -0.076842643320560455,
                "y": 0.15983131527900696,
                "z": 0.42642933130264282,
                "w": 0.88696515560150146
            },
            "scale": {
                "x": 0.99999994039535522,
                "y": 1,
                "z": 1
            }
        },
        {
            "type": 2,
            "parentUID": 417723200,
            "position": {
                "x": -1.6931518316268921,
                "y": -2.2955915927886963,
                "z": 0.63886713981628418
            },
            "rotation": {
                "x": -0.2416081428527832,
                "y": -0.32758599519729614,
                "z": 0.091182038187980652,
                "w": 0.90884482860565186
            },
            "scale": {
                "x": 1,
                "y": 1,
                "z": 0.99999994039535522
            }
        },
        {
            "type": 2,
            "parentUID": -256659200,
            "position": {
                "x": 0,
                "y": 0,
                "z": 0
            },
            "rotation": {
                "x": 0.88696515560150146,
                "y": 0.42642930150032043,
                "z": -0.15983133018016815,
                "w": -0.076842702925205231
            },
            "scale": {
                "x": 1,
                "y": 0.99999994039535522,
                "z": 1
            }
        },
        {
            "type": 2,
            "parentUID": -702691008,
            "position": {
                "x": 0.041702710092067719,
                "y": -0.41237720847129822,
                "z": 0.45352193713188171
            },
            "rotation": {
                "x": 0,
                "y": 0,
                "z": 0,
                "w": 1
            },
            "scale": {
                "x": 1,
                "y": 1,
                "z": 1
            }
        },
        {
            "type": 2,
            "parentUID": -805299200,
            "position": {
                "x": 0.20675966143608093,
                "y": -0.2876608669757843,
                "z": 0.29150724411010742
            },
            "rotation": {
                "x": 0,
                "y": 0,
                "z": 0,
                "w": 1
            },
            "scale": {
                "x": 1,
                "y": 1,
                "z": 1
            }
        },
        {
            "type": 2,
            "parentUID": 1012490048,
            "position": {
                "x": 0.12375076860189438,
                "y": -0.3016989529132843,
                "z": 0.17823728919029236
            },
            "rotation": {
                "x": 0,
                "y": 0,
                "z": 0,
                "w": 1
            },
            "scale": {
                "x": 1,
                "y": 1,
                "z": 1
            }
        },
        {
            "type": 2,
            "parentUID": -1520976896,
            "position": {
                "x": 0.1508205384016037,
                "y": -0.39155444502830505,
                "z": 0.10519598424434662
            },
            "rotation": {
                "x": 0,
                "y": 0,
                "z": 0,
                "w": 1
            },
            "scale": {
                "x": 1,
                "y": 1,
                "z": 1
            }
        },
        {
            "type": 2,
            "parentUID": -211123744,
            "position": {
                "x": -0.35671427845954895,
                "y": -1.2270692586898804,
                "z": 0.48711788654327393
            },
            "rotation": {
                "x": 0,
                "y": 0,
                "z": 0,
                "w": 1
            },
            "scale": {
                "x": 1,
                "y": 1,
                "z": 1
            }
        },
        {
            "type": 2,
            "parentUID": -1775365632,
            "position": {
                "x": 0.059540156275033951,
                "y": -0.49339038133621216,
                "z": 0.014718991704285145
            },
            "rotation": {
                "x": 0,
                "y": 0,
                "z": 0,
                "w": 1
            },
            "scale": {
                "x": 1,
                "y": 1,
                "z": 1
            }
        },
        {
            "type": 2,
            "parentUID": 250299104,
            "position": {
                "x": 0.16221265494823456,
                "y": -0.39550837874412537,
                "z": -0.031540244817733765
            },
            "rotation": {
                "x": 0,
                "y": 0,
                "z": 0,
                "w": 1
            },
            "scale": {
                "x": 1,
                "y": 1,
                "z": 1
            }
        },
        {
            "type": 2,
            "parentUID": 693538944,
            "position": {
                "x": 0.21741804480552673,
                "y": -0.33433762192726135,
                "z": -0.030045274645090103
            },
            "rotation": {
                "x": 0,
                "y": 0,
                "z": 0,
                "w": 1
            },
            "scale": {
                "x": 1,
                "y": 1,
                "z": 1
            }
        },
        {
            "type": 2,
            "parentUID": -1711461376,
            "position": {
                "x": -0.30260848999023438,
                "y": -1.2290678024291992,
                "z": -0.25764608383178711
            },
            "rotation": {
                "x": 0,
                "y": 0,
                "z": 0,
                "w": 1
            },
            "scale": {
                "x": 1,
                "y": 1,
                "z": 1
            }
        },
        {
            "type": 2,
            "parentUID": 968746688,
            "position": {
                "x": 0.084514856338500977,
                "y": -0.52465677261352539,
                "z": 0.028078421950340271
            },
            "rotation": {
                "x": 0,
                "y": 0,
                "z": 0,
                "w": 1
            },
            "scale": {
                "x": 1,
                "y": 1,
                "z": 1
            }
        },
        {
            "type": 2,
            "parentUID": -2058729216,
            "position": {
                "x": 0.15169514715671539,
                "y": -0.29501593112945557,
                "z": 0.04000246524810791
            },
            "rotation": {
                "x": 0,
                "y": 0,
                "z": 0,
                "w": 1
            },
            "scale": {
                "x": 1,
                "y": 1,
                "z": 1
            }
        },
        {
            "type": 2,
            "parentUID": -584565952,
            "position": {
                "x": 0.18495477735996246,
                "y": -0.29434129595756531,
                "z": 0.070103347301483154
            },
            "rotation": {
                "x": 0,
                "y": 0,
                "z": 0,
                "w": 1
            },
            "scale": {
                "x": 1,
                "y": 1,
                "z": 1
            }
        },
        {
            "type": 2,
            "parentUID": 1639236352,
            "position": {
                "x": -3.7933696717118437e-07,
                "y": 1.5727609395980835,
                "z": 1.2803964182239724e-06
            },
            "rotation": {
                "x": -0.062142219394445419,
                "y": 0.21665067970752716,
                "z": -0.042345061898231506,
                "w": 0.97334879636764526
            },
            "scale": {
                "x": 1,
                "y": 1,
                "z": 1
            }
        },
        {
            "type": 2,
            "parentUID": -591561792,
            "position": {
                "x": 2.3840864571411657e-07,
                "y": 1.5850509405136108,
                "z": 0.29454630613327026
            },
            "rotation": {
                "x": -0.057750973850488663,
                "y": 0.21987025439739227,
                "z": 0.022292366251349449,
                "w": 0.97356307506561279
            },
            "scale": {
                "x": 1,
                "y": 1,
                "z": 1
            }
        },
        {
            "type": 2,
            "parentUID": 1633352576,
            "position": {
                "x": 3.0770299434661865,
                "y": -0.3280312716960907,
                "z": 0.38774123787879944
            },
            "rotation": {
                "x": 0,
                "y": 0,
                "z": 0.63938921689987183,
                "w": 0.76888322830200195
            },
            "scale": {
                "x": 1,
                "y": 1,
                "z": 1
            }
        },
        {
            "type": 2,
            "parentUID": -768364992,
            "position": {
                "x": 1.3073379993438721,
                "y": -0.40782546997070313,
                "z": 1.7765474319458008
            },
            "rotation": {
                "x": -0.53729963302612305,
                "y": 0,
                "z": 0,
                "w": 0.84339141845703125
            },
            "scale": {
                "x": 1,
                "y": 1,
                "z": 1
            }
        },
        {
            "type": 2,
            "parentUID": 816238528,
            "position": {
                "x": 0,
                "y": 0,
                "z": 0
            },
            "rotation": {
                "x": 0,
                "y": 0,
                "z": 0,
                "w": 1
            },
            "scale": {
                "x": 1,
                "y": 1,
                "z": 1
            }
        },
        {
            "type": 2,
            "parentUID": 408108192,
            "position": {
                "x": 0,
                "y": 0,
                "z": 0
            },
            "rotation": {
                "x": 0,
                "y": 0,
                "z": 0,
                "w": 1
            },
            "scale": {
                "x": 1,
                "y": 1,
                "z": 1
            }
        },
        {
            "type": 2,
            "parentUID": -1438609280,
            "position": {
                "x": 0,
                "y": 0,
                "z": 0
            },
            "rotation": {
                "x": 0,
                "y": 0,
                "z": 0,
                "w": 1
            },
            "scale": {
                "x": 1,
                "y": 1,
                "z": 1
            }
        },
        {
            "type": 2,
            "parentUID": 243113328,
            "position": {
                "x": 0,
                "y": 0,
                "z": 0
            },
            "rotation": {
                "x": 0,
                "y": 0,
                "z": 0,
                "w": 1
            },
            "scale": {
                "x": 1,
                "y": 1,
                "z": 1
            }
        }
    ]
}